README.md
setup.py
co6co_win/__init__.py
co6co_win/services.py
co6co_win.egg-info/PKG-INFO
co6co_win.egg-info/SOURCES.txt
co6co_win.egg-info/dependency_links.txt
co6co_win.egg-info/requires.txt
co6co_win.egg-info/top_level.txt
co6co_win.egg-info/zip-safe