Metadata-Version: 2.1
Name: co6co-win
Version: 0.0.1
Summary: Win基础模块
Home-page: http://git.hub.com/co6co
Author: co6co
Author-email: co6co@qq.com
Classifier: Programming Language :: Python :: 3
Classifier: Programming Language :: Python :: 3.6
Requires-Dist: pywin32
